across_client/__init__.py
across_client/constants.py
across_client/functions.py
across_client/py.typed
across_client/across/__init__.py
across_client/across/resolve.py
across_client/across/schema.py
across_client/base/__init__.py
across_client/base/common.py
across_client/base/coords.py
across_client/base/daterange.py
across_client/base/schema.py
across_client/base/user.py
across_client/burstcube/__init__.py
across_client/burstcube/constants.py
across_client/burstcube/fov.py
across_client/burstcube/schema.py
across_client/burstcube/toorequest.py
across_burstcube-0.4.dist-info/METADATA
across_burstcube-0.4.dist-info/WHEEL
across_burstcube-0.4.dist-info/top_level.txt
across_burstcube-0.4.dist-info/RECORD
